CHANGES.txt
LICENSE
MANIFEST.in
README.rst
setup.py
scrobbler/__init__.py
scrobbler/info.py
scrobbler/scrobbler.py
scrobblerh.egg-info/PKG-INFO
scrobblerh.egg-info/SOURCES.txt
scrobblerh.egg-info/dependency_links.txt
scrobblerh.egg-info/entry_points.txt
scrobblerh.egg-info/requires.txt
scrobblerh.egg-info/top_level.txt