Metadata-Version: 1.1
Name: scrobblerh
Version: 1.1.3.post1
Summary: A command-line Last.fm scrobbler and a now-playing status updater.
Home-page: https://bitbucket.org/hauzer/scrobbler/
Author: Никола "hauzer" Вукосављевић
Author-email: hauzer@gmx.com
License: GPLv3
Download-URL: https://bitbucket.org/hauzer/scrobbler/downloads
Platform: UNKNOWN
Classifier: Development Status :: 4 - Beta
Classifier: Environment :: Console
Classifier: Intended Audience :: End Users/Desktop
Classifier: License :: OSI Approved :: GNU General Public License v3 (GPLv3)
Classifier: Operating System :: OS Independent
Classifier: Programming Language :: Python :: 3
